youtube_upload/__init__.py
youtube_upload/client.py
youtube_upload/oauth_template.py
pillar_youtube_upload-0.3.0.dist-info/LICENSE
pillar_youtube_upload-0.3.0.dist-info/METADATA
pillar_youtube_upload-0.3.0.dist-info/WHEEL
pillar_youtube_upload-0.3.0.dist-info/top_level.txt
pillar_youtube_upload-0.3.0.dist-info/RECORD
