Metadata-Version: 2.1
Name: pillar-youtube-upload
Version: 0.3.0
Summary: Upload YouTube videos from Python and more.
Home-page: https://github.com/pillargg/youtube-upload
Author: PillarGG
Author-email: opensource@pillar.gg
License: UNKNOWN
Platform: UNKNOWN
Classifier: Programming Language :: Python :: 3
Classifier: License :: OSI Approved :: MIT License
Classifier: Operating System :: OS Independent
Requires-Python: >=3.6
Requires-Dist: httplib2 (>=0.18.1)
Requires-Dist: google-auth (>=1.22.1)
Requires-Dist: google-api-core (>=1.23.0)
Requires-Dist: google-api-python-client (>=1.12.5)
Requires-Dist: oauth2client (>=4.1.3)
